Temp/test_alchemy_cat_config/dump.py
alchemy_cat/__init__.py
alchemy_cat/acplot/__init__.py
alchemy_cat/acplot/figure_wall.py
alchemy_cat/acplot/plot_conf_matrix.py
alchemy_cat/acplot/shuffle_ch.py
alchemy_cat/acplot/subplots_row_col.py
alchemy_cat/acplot/utils.py
alchemy_cat/alg/__init__.py
alchemy_cat/alg/clamp_softmax.py
alchemy_cat/alg/cnn_align.py
alchemy_cat/alg/complement_entropy_confidence.py
alchemy_cat/alg/dense_crf.py
alchemy_cat/alg/eval_cams.py
alchemy_cat/alg/masked_softmax.py
alchemy_cat/alg/msc_flip_inference.py
alchemy_cat/alg/normalize_tensor.py
alchemy_cat/alg/resize.py
alchemy_cat/alg/sampling.py
alchemy_cat/alg/slide_inference.py
alchemy_cat/alg/utils.py
alchemy_cat/alg/window_slides.py
alchemy_cat/contrib/__init__.py
alchemy_cat/contrib/module_init_fns.py
alchemy_cat/contrib/build_dt/__init__.py
alchemy_cat/contrib/build_dt/voc_object_detection/__init__.py
alchemy_cat/contrib/build_dt/voc_object_detection/rw_annotation.py
alchemy_cat/contrib/build_dt/voc_object_detection/scripts/__init__.py
alchemy_cat/contrib/build_dt/voc_object_detection/scripts/split_set.py
alchemy_cat/contrib/build_dt/voc_object_detection/scripts/viz_annotation.py
alchemy_cat/contrib/coco/__init__.py
alchemy_cat/contrib/coco/coco14seg.py
alchemy_cat/contrib/coco/scripts/__init__.py
alchemy_cat/contrib/coco/scripts/coco上色.py
alchemy_cat/contrib/coco/scripts/convert_coco81to91.py
alchemy_cat/contrib/coco/scripts/convert_coco91to81.py
alchemy_cat/contrib/constant/__init__.py
alchemy_cat/contrib/constant/dt_constant.py
alchemy_cat/contrib/evaluation/__init__.py
alchemy_cat/contrib/evaluation/semantics_segmentation/__init__.py
alchemy_cat/contrib/evaluation/semantics_segmentation/eval_preds.py
alchemy_cat/contrib/loss/ASL.py
alchemy_cat/contrib/loss/__init__.py
alchemy_cat/contrib/loss/cl_loss.py
alchemy_cat/contrib/loss/seg_criterion.py
alchemy_cat/contrib/loss/wsss/__init__.py
alchemy_cat/contrib/loss/wsss/balanced_seed_loss.py
alchemy_cat/contrib/loss/wsss/boundary_loss.py
alchemy_cat-0.0.11.dist-info/licenses/LICENSE
alchemy_cat-0.0.11.dist-info/METADATA
alchemy_cat-0.0.11.dist-info/WHEEL
alchemy_cat-0.0.11.dist-info/top_level.txt
alchemy_cat-0.0.11.dist-info/RECORD
