Metadata-Version: 2.4
Name: alchemy_cat
Version: 0.0.11
Summary: Alchemy Cat —— 🔥Config System for SOTA
Author-email: HAL-42 <hal_42@zju.edu.cn>
License:  Apache License
Project-URL: Homepage, https://github.com/HAL-42/AlchemyCat
Project-URL: Issues, https://github.com/HAL-42/AlchemyCat/issues
Keywords: config,deep learning,parameter tuning,hyperparameter
Classifier: Programming Language :: Python :: 3
Classifier: License :: OSI Approved :: Apache Software License
Classifier: Operating System :: OS Independent
Requires-Python: >=3.8
License-File: LICENSE
Requires-Dist: numpy
Requires-Dist: tqdm
Requires-Dist: colorama
Requires-Dist: pandas
Requires-Dist: openpyxl
Requires-Dist: loguru
Requires-Dist: psutil
Requires-Dist: gpustat>=0.6.0
Requires-Dist: Pillow
Requires-Dist: regex>=2024.11.6
Requires-Dist: pytest>=8.3.5
Provides-Extra: full
Requires-Dist: addict>=2.4.0; extra == "full"
Requires-Dist: PyYAML>=6.0; extra == "full"
Requires-Dist: setuptools>=68.0.0; extra == "full"
Requires-Dist: opencv-python>=4.8.0.74; extra == "full"
Requires-Dist: scipy>=1.10.1; extra == "full"
Requires-Dist: matplotlib>=3.7.1; extra == "full"
Requires-Dist: torchvision>=0.15.2; extra == "full"
Requires-Dist: lmdb>=1.4.1; extra == "full"
Requires-Dist: seaborn>=0.12.2; extra == "full"
Requires-Dist: imagesize>=1.4.1; extra == "full"
Requires-Dist: scikit-image>=0.20.0; extra == "full"
Requires-Dist: scikit-learn>=1.2.2; extra == "full"
Requires-Dist: xlwings>=0.30.10; extra == "full"
Dynamic: license-file
